torchpipeline/__init__.py
torchpipeline/pipe.py
torchpipeline/pipeline.py
torchpipeline/typing.py
torchpipeline/coupling/__init__.py
torchpipeline/coupling/coupling.py
torchpipeline/coupling/default_coupling.py
torchpipeline/coupling/generic_coupling.py
torchpipeline/routing/__init__.py
torchpipeline/routing/default_router.py
torchpipeline/routing/generic_router.py
torchpipeline/routing/router.py
torchpipeline-0.1.0.dev0.data/data/LICENSE
torchpipeline-0.1.0.dev0.data/data/README.md
torchpipeline-0.1.0.dev0.dist-info/LICENSE
torchpipeline-0.1.0.dev0.dist-info/METADATA
torchpipeline-0.1.0.dev0.dist-info/WHEEL
torchpipeline-0.1.0.dev0.dist-info/top_level.txt
torchpipeline-0.1.0.dev0.dist-info/RECORD
