Metadata-Version: 2.1
Name: torchpipeline
Version: 0.1.0.dev0
Summary: UNKNOWN
Home-page: https://github.com/phohenecker/pytorch-pipeline
Author: Patrick Hohenecker
Author-email: patrick.hohenecker@gmx.at
License: BSD-3-Clause
Platform: UNKNOWN
Classifier: Programming Language :: Python :: 3.9
Requires-Python: >=3.9
License-File: LICENSE
Requires-Dist: insanity (>=2017.1)
Requires-Dist: torch (>=1.8.1)
